harvester/harvester.py
harvester/models.py
harvester/translate.py
frost_harvester-0.1.0.dist-info/METADATA
frost_harvester-0.1.0.dist-info/WHEEL
frost_harvester-0.1.0.dist-info/RECORD
